alibabacloud_nbftestpop20210712_195030595/__init__.py
alibabacloud_nbftestpop20210712_195030595/client.py
alibabacloud_nbftestpop20210712_195030595/models.py
alibabacloud_nbftestpop20210712_195030595-1.0.0.dist-info/LICENSE
alibabacloud_nbftestpop20210712_195030595-1.0.0.dist-info/METADATA
alibabacloud_nbftestpop20210712_195030595-1.0.0.dist-info/WHEEL
alibabacloud_nbftestpop20210712_195030595-1.0.0.dist-info/top_level.txt
alibabacloud_nbftestpop20210712_195030595-1.0.0.dist-info/RECORD
